{
  "cluster.shards": {
    "documentation": "",
    "methods": ["GET", "POST"],
    "url": {
      "path": "/_search_shards",
      "paths": ["/_search_shards", "/{index}/_search_shards", "/{index}/{type}/_search_shards"],
      "parts": {
        "index": {
        },
        "type": {
        }
      },
      "params": {
        "ignore_indices": {
        },
        "index": {
        },
        "local": {
        },
        "preference": {
        },
        "routing": {
        },
        "type": {
        }
      }
    },
    "body": null
  }
}
