{
  "cluster.put_component_template": {
    "documentation": {
      "url": "https://www.elastic.co/docs/api/doc/elasticsearch/operation/operation-cluster-put-component-template",
      "description": "Create or update a component template"
    },
    "stability": "stable",
    "visibility": "public",
    "headers": {
      "accept": [
        "application/json"
      ],
      "content_type": [
        "application/json"
      ]
    },
    "url": {
      "paths": [
        {
          "path": "/_component_template/{name}",
          "methods": [
            "PUT",
            "POST"
          ],
          "parts": {
            "name": {
              "type": "string",
              "description": "The name of the template"
            }
          }
        }
      ]
    },
    "params": {
      "create": {
        "type": "boolean",
        "description": "Whether the index template should only be added if new or can also replace an existing one",
        "default": false
      },
      "cause": {
        "type": "string",
        "description": "User defined reason for create the component template",
        "default": "api"
      },
      "master_timeout": {
        "type": "time",
        "default": "30s",
        "description": "Specify timeout for connection to master"
      }
    },
    "body": {
      "description": "The template definition",
      "required": true
    }
  }
}
