{
  "indices.get_data_stream": {
    "documentation": {
      "url": "https://www.elastic.co/docs/api/doc/elasticsearch/operation/operation-indices-get-data-stream",
      "description": "Get data streams"
    },
    "stability": "stable",
    "visibility": "public",
    "headers": {
      "accept": [
        "application/json"
      ]
    },
    "url": {
      "paths": [
        {
          "path": "/_data_stream",
          "methods": [
            "GET"
          ]
        },
        {
          "path": "/_data_stream/{name}",
          "methods": [
            "GET"
          ],
          "parts": {
            "name": {
              "type": "list",
              "description": "A comma-separated list of data streams to get; use `*` to get all data streams"
            }
          }
        }
      ]
    },
    "params": {
      "expand_wildcards": {
        "type": "list",
        "options": [
          "open",
          "closed",
          "hidden",
          "none",
          "all"
        ],
        "default": "open",
        "description": "Whether wildcard expressions should get expanded to open or closed indices (default: open)"
      },
      "include_defaults": {
        "type": "boolean",
        "default": false,
        "description": "Return all relevant default configurations for the data stream (default: false)"
      },
      "master_timeout": {
        "type": "time",
        "default": "30s",
        "description": "Specify timeout for connection to master"
      },
      "verbose": {
        "type": "boolean",
        "default": false,
        "description": "Whether the maximum timestamp for each data stream should be calculated and returned (default: false)"
      }
    }
  }
}
